automl_alex/__init__.py
automl_alex/_base.py
automl_alex/_encoders.py
automl_alex/_logger.py
automl_alex/automl_alex.py
automl_alex/cross_validation.py
automl_alex/data_prepare.py
automl_alex/models/__init__.py
automl_alex/models/model_catboost.py
automl_alex/models/model_lightgbm.py
automl_alex/models/model_xgboost.py
automl_alex/models/sklearn_models.py
automl_alex/optimizer.py
automl_alex-2023.3.11.dist-info/LICENSE
automl_alex-2023.3.11.dist-info/WHEEL
automl_alex-2023.3.11.dist-info/METADATA
automl_alex-2023.3.11.dist-info/RECORD
