Metadata-Version: 2.1
Name: automl-alex
Version: 2023.3.11
Summary: State-of-the art Automated Machine Learning python library for Tabular Data
License: MIT
Author: Alex-Lekov
Author-email: 61644712+Alex-Lekov@users.noreply.github.com
Requires-Python: >=3.8,<3.11
Classifier: License :: OSI Approved :: MIT License
Classifier: Programming Language :: Python :: 3
Classifier: Programming Language :: Python :: 3.10
Classifier: Programming Language :: Python :: 3.8
Classifier: Programming Language :: Python :: 3.9
Requires-Dist: catboost (>=1.1.1,<2.0.0)
Requires-Dist: category-encoders (>=2.6.0,<3.0.0)
Requires-Dist: lightgbm (>=3.3.5,<4.0.0)
Requires-Dist: loguru (>=0.6.0,<0.7.0)
Requires-Dist: nbformat (>=5.7.3,<6.0.0)
Requires-Dist: numpy (>=1.18,<2.0)
Requires-Dist: optuna (>=3.1.0,<4.0.0)
Requires-Dist: optuna-dashboard (>=0.8.1,<0.9.0)
Requires-Dist: pandas (>=1.5.3,<2.0.0)
Requires-Dist: psutil (>=5.9.4,<6.0.0)
Requires-Dist: scikit-learn (>=1.2.2,<2.0.0)
Requires-Dist: seaborn (>=0.12.2,<0.13.0)
Requires-Dist: tqdm (>=4.65.0,<5.0.0)
Requires-Dist: xgboost (>=1.7.4,<2.0.0)
